COPYRIGHT.txt
HISTORY.txt
INSTALL.txt
LICENSE.txt
MANIFEST.in
setup.py
template2pdf/__init__.py
template2pdf/utils.py
template2pdf.egg-info/PKG-INFO
template2pdf.egg-info/SOURCES.txt
template2pdf.egg-info/dependency_links.txt
template2pdf.egg-info/top_level.txt
template2pdf.egg-info/zip-safe
template2pdf/dj/__init__.py
template2pdf/dj/templates/base.rml
template2pdf/dj/templatetags/__init__.py
template2pdf/dj/templatetags/pdf_tags.py
template2pdf/fsk/__init__.py
template2pdf/fsk/templates/base.rml
template2pdf/kfw/__init__.py
template2pdf/kfw/urls.py
template2pdf/kfw/templates/base.rml
template2pdf/t2p/COPYRIGHT.txt
template2pdf/t2p/LICENSE.txt
template2pdf/t2p/__init__.py
template2pdf/t2p/tests.py
template2pdf/t2p/trml2pdf.py
template2pdf/t2p/utils.py