Metadata-Version: 1.0
Name: template2pdf
Version: 0.6.5
Summary: Renders Django/Jinja2 templates into PDF.
Home-page: http://code.google.com/p/template2pdf/
Author: Yasushi Masuda, Accense Technology, Inc.
Author-email: ymasuda at accense.com or whosaysni at gmail.com
License: LGPL
Platform: UNKNOWN
Classifier: Development Status :: 4 - Beta
Classifier: Intended Audience :: Developers
Classifier: License :: OSI Approved :: GNU Library or Lesser General Public License (LGPL)
Classifier: Programming Language :: Python
Classifier: Topic :: Software Development :: Libraries :: Python Modules
